gbvision/__init__.py
gbvision/constants/__init__.py
gbvision/constants/images.py
gbvision/constants/math.py
gbvision/constants/net.py
gbvision/constants/system.py
gbvision/constants/types.py
gbvision/constants/video.py
gbvision/exceptions/__init__.py
gbvision/exceptions/could_not_read_frame_exception.py
gbvision/exceptions/device_not_found_exception.py
gbvision/exceptions/stream_closed.py
gbvision/exceptions/tcp_stream_closed.py
gbvision/exceptions/vision_exception.py
gbvision/exceptions/vision_warning.py
gbvision/gui/__init__.py
gbvision/gui/camera_window.py
gbvision/gui/feed_window.py
gbvision/gui/opencv_window.py
gbvision/gui/readable_window.py
gbvision/gui/recording_camera_window.py
gbvision/gui/recording_feed_window.py
gbvision/gui/recording_opencv_window.py
gbvision/gui/recording_readable_window.py
gbvision/gui/recording_stream_window.py
gbvision/gui/recording_window.py
gbvision/gui/recording_wrapper_opencv_window.py
gbvision/gui/stream_window.py
gbvision/gui/window.py
gbvision/gui/wrapper_opencv_window.py
gbvision/gui/wrapper_window.py
gbvision/models/__init__.py
gbvision/models/basic_ops.py
gbvision/models/cameras.py
gbvision/models/contours.py
gbvision/models/system.py
gbvision/tools/__init__.py
gbvision/tools/drawing_tools.py
gbvision/tools/finding_tools.py
gbvision/tools/image_tools.py
gbvision/tools/list_tools.py
gbvision/tools/math_tools.py
gbvision/utils/__init__.py
gbvision/utils/async_readable.py
gbvision/utils/game_object.py
gbvision/utils/pipeline.py
gbvision/utils/readable.py
gbvision/utils/releasable.py
gbvision/utils/tracker.py
gbvision/utils/cameras/__init__.py
gbvision/utils/cameras/async_camera.py
gbvision/utils/cameras/async_usb_camera.py
gbvision/utils/cameras/camera.py
gbvision/utils/cameras/camera_data.py
gbvision/utils/cameras/camera_list.py
gbvision/utils/cameras/empty_camera.py
gbvision/utils/cameras/stream_camera.py
gbvision/utils/cameras/streaming_camera.py
gbvision/utils/cameras/usb_camera.py
gbvision-1.0.1.dist-info/LICENSE
gbvision-1.0.1.dist-info/METADATA
gbvision-1.0.1.dist-info/WHEEL
gbvision-1.0.1.dist-info/top_level.txt
gbvision-1.0.1.dist-info/RECORD
